geoarrow/types/__init__.py
geoarrow/types/constants.py
geoarrow/types/crs.py
geoarrow/types/type_pyarrow.py
geoarrow/types/type_spec.py
geoarrow_types-0.2.0.dist-info/METADATA
geoarrow_types-0.2.0.dist-info/WHEEL
geoarrow_types-0.2.0.dist-info/top_level.txt
geoarrow_types-0.2.0.dist-info/RECORD
