Metadata-Version: 2.1
Name: geoarrow-types
Version: 0.2.0
Author-email: Dewey Dunnington <dewey@dunnington.ca>
License: Apache-2.0
Project-URL: homepage, https://geoarrow.org
Project-URL: repository, https://github.com/geoarrow/geoarrow-python
Requires-Python: >=3.8
Provides-Extra: test
Requires-Dist: pytest ; extra == 'test'
Requires-Dist: pyarrow ; extra == 'test'
